README.md
setup.py
brookmount/__init__.py
brookmount/brookmount.py
brookmount/sac.py
brookmount.egg-info/PKG-INFO
brookmount.egg-info/SOURCES.txt
brookmount.egg-info/dependency_links.txt
brookmount.egg-info/entry_points.txt
brookmount.egg-info/top_level.txt