Metadata-Version: 2.1
Name: brookmount
Version: 0.0.57
Summary: python package for brookmount.
Home-page: https://github.com/brookmount/pip
Author: reyan
